setup.cfg
setup.py
TracMacroTotalField.egg-info/PKG-INFO
TracMacroTotalField.egg-info/SOURCES.txt
TracMacroTotalField.egg-info/dependency_links.txt
TracMacroTotalField.egg-info/entry_points.txt
TracMacroTotalField.egg-info/top_level.txt
totalfield/__init__.py
totalfield/total_field.py