Metadata-Version: 1.0
Name: TracMacroTotalField
Version: 0.0.2
Summary: Trac Macro to sum a custom field on a query
Home-page: https://github.com/pierrejean-coudert/trac_totalfield_plugin
Author: Pierre-Jean Coudert
Author-email: coudert@free.fr
License: MIT
Download-URL: https://github.com/peterldowns/mypackage/tarball/0.0.2
Platform: UNKNOWN
